scraper_bot/__init__.py
scraper_bot/__main__.py
scraper_bot/_version.py
scraper_bot/cache/__init__.py
scraper_bot/cache/cache.py
scraper_bot/cache/disk_cache.py
scraper_bot/cache/dummy_cache.py
scraper_bot/cache/exceptions.py
scraper_bot/cache/maker.py
scraper_bot/cache/redis_cache.py
scraper_bot/exceptions.py
scraper_bot/logging/__init__.py
scraper_bot/logging/logging.py
scraper_bot/notifications/__init__.py
scraper_bot/notifications/notifications.py
scraper_bot/scraper/__init__.py
scraper_bot/scraper/browser_manager.py
scraper_bot/scraper/exceptions.py
scraper_bot/scraper/scraper.py
scraper_bot/scraper/scraper_task.py
scraper_bot/scraper/scraper_task_result.py
scraper_bot/scraper/scraper_task_result_entity.py
scraper_bot/scraper_bot/__init__.py
scraper_bot/scraper_bot/scraper_bot.py
scraper_bot/settings/__init__.py
scraper_bot/settings/browser.py
scraper_bot/settings/notifications.py
scraper_bot/settings/settings.py
scraper_bot/settings/task.py
scraper_bot/utilities/__init__.py
scraper_bot/utilities/apprise_uri.py
scraper_bot/utilities/disk_cache_dsn.py
scraper_bot-1.3.2.dist-info/LICENSE
scraper_bot-1.3.2.dist-info/METADATA
scraper_bot-1.3.2.dist-info/WHEEL
scraper_bot-1.3.2.dist-info/entry_points.txt
scraper_bot-1.3.2.dist-info/RECORD
