Metadata-Version: 2.1
Name: scraper-bot
Version: 1.3.2
Summary: A telegram bot to stay tuned on real estate ads
Home-page: https://github.com/RobertoBochet/bot-scraper.git
License: GPL-3.0-or-later
Author: Roberto Bochet
Author-email: r@robertobochet.me
Requires-Python: >=3.12,<4.0
Classifier: Development Status :: 5 - Production/Stable
Classifier: Framework :: AsyncIO
Classifier: Framework :: Pydantic
Classifier: License :: OSI Approved :: GNU General Public License v3 or later (GPLv3+)
Classifier: Operating System :: OS Independent
Classifier: Programming Language :: Python :: 3
Classifier: Programming Language :: Python :: 3.12
Classifier: Typing :: Typed
Requires-Dist: aiolimiter (>=1.1.0,<2.0.0)
Requires-Dist: apprise (>=1.9.0,<2.0.0)
Requires-Dist: black (>=24.10.0,<25.0.0)
Requires-Dist: diskcache (>=5.6.3,<6.0.0)
Requires-Dist: jinja2 (>=3.1.4,<4.0.0)
Requires-Dist: playwright (>=1.48.0,<2.0.0)
Requires-Dist: playwright-stealth (>=1.0.6,<2.0.0)
Requires-Dist: pydantic (>=2.9.2,<3.0.0)
Requires-Dist: pydantic-settings (>=2.6.1,<3.0.0)
Requires-Dist: redis (>=5.2.0,<6.0.0)
Requires-Dist: setuptools (>=75.5.0,<76.0.0)
Requires-Dist: termcolor (>=2.5.0,<3.0.0)
Project-URL: Repository, https://github.com/RobertoBochet/bot-scraper.git
